delete_last_comma/__init__.py
delete_last_comma/core.py
delete_last_comma/helpers.py
delete_last_comma-0.1.2.dist-info/LICENSE
delete_last_comma-0.1.2.dist-info/METADATA
delete_last_comma-0.1.2.dist-info/WHEEL
delete_last_comma-0.1.2.dist-info/top_level.txt
delete_last_comma-0.1.2.dist-info/RECORD
