Metadata-Version: 2.1
Name: delete-last-comma
Version: 0.1.2
Summary: json形式文字列中のいわゆるケツカンマを削除する
Home-page: https://github.com/anaakikutushita/delete_last_comma
Author: Atsushi Suzuki
Author-email: atushi_anaaki@yahoo.co.jp
License: Copyright (c) 2017, Kenneth Reitz
